{"season_1":[{"episode_1":[["https://video.sibnet.ru/shell.php?videoid=3912069","https://odnoklassniki.ru/videoembed/2660871637587","https://vidmoly.to/embed-3s54pjev5gmm.html","https://sendvid.com/embed/ayclxltu","https://my.mail.ru/mail/animeizlettr/video/embed/_myvideo/287"]],"episode_2":[["https://video.sibnet.ru/shell.php?videoid=3912072","https://odnoklassniki.ru/videoembed/2660875110995","https://vidmoly.to/embed-uymblw3lllt2.html","https://sendvid.com/embed/k4iw27t3","https://my.mail.ru/mail/animeizlettr/video/embed/_myvideo/288"]],"episode_3":[["https://video.sibnet.ru/shell.php?videoid=3912074","https://odnoklassniki.ru/videoembed/2660876552787","https://vidmoly.to/embed-7vfyv676fxte.html","https://sendvid.com/embed/e6ymic0w","https://my.mail.ru/mail/animeizlettr/video/embed/_myvideo/289"]],"episode_4":[["https://video.sibnet.ru/shell.php?videoid=3912075","https://odnoklassniki.ru/videoembed/2660878060115","https://vidmoly.to/embed-16qlkf62ukw2.html","https://sendvid.com/embed/ugon70ry","https://my.mail.ru/mail/animeizlettr/video/embed/_myvideo/290"]],"episode_5":[["https://video.sibnet.ru/shell.php?videoid=3912077","https://odnoklassniki.ru/videoembed/2660879370835","https://vidmoly.to/embed-gl3k207dhcdc.html","https://sendvid.com/embed/avsxjj1g","https://my.mail.ru/mail/animeizlettr/video/embed/_myvideo/291"]],"episode_6":[["https://video.sibnet.ru/shell.php?videoid=3912079","https://odnoklassniki.ru/videoembed/2660881599059","https://vidmoly.to/embed-ojubajxommc7.html","https://sendvid.com/embed/byr67yqe","https://my.mail.ru/mail/animeizlettr/video/embed/_myvideo/292"]],"episode_7":[["https://video.sibnet.ru/shell.php?videoid=3912082","https://odnoklassniki.ru/videoembed/2660886186579","https://vidmoly.to/embed-93zu2acryd1c.html","https://sendvid.com/embed/j3evrrlg","https://my.mail.ru/mail/animeizlettr/video/embed/_myvideo/293"]],"episode_8":[["https://video.sibnet.ru/shell.php?videoid=3912084","https://odnoklassniki.ru/videoembed/2660890839635","https://vidmoly.to/embed-igz9r5kdfl03.html","https://sendvid.com/embed/tjwda4lb","https://my.mail.ru/mail/animeizlettr/video/embed/_myvideo/294"]],"episode_9":[["https://video.sibnet.ru/shell.php?videoid=3912086","https://odnoklassniki.ru/videoembed/2660897983059","https://vidmoly.to/embed-gsc7m4mbm26w.html","https://sendvid.com/embed/ksb7jruz","https://my.mail.ru/mail/animeizlettr/video/embed/_myvideo/295"]],"episode_10":[["https://video.sibnet.ru/shell.php?videoid=3912088","https://odnoklassniki.ru/videoembed/2660900735571","https://vidmoly.to/embed-3jqjodd2fg8q.html","https://sendvid.com/embed/rnebfco1","https://my.mail.ru/mail/animeizlettr/video/embed/_myvideo/296"]],"episode_11":[["https://video.sibnet.ru/shell.php?videoid=3912091","https://odnoklassniki.ru/videoembed/2660901522003","https://vidmoly.to/embed-ul42ouf174co.html","https://sendvid.com/embed/voocis4d","https://my.mail.ru/mail/animeizlettr/video/embed/_myvideo/297"]],"episode_12":[["https://video.sibnet.ru/shell.php?videoid=3912093","https://odnoklassniki.ru/videoembed/2660903422547","https://vidmoly.to/embed-l4v3rvs1ivh1.html","https://sendvid.com/embed/t9kiugq7","https://my.mail.ru/mail/animeizlettr/video/embed/_myvideo/298"]],"episode_13":[["https://video.sibnet.ru/shell.php?videoid=3912094","https://odnoklassniki.ru/videoembed/2660908010067","https://vidmoly.to/embed-3b0htjo8q1cs.html","https://sendvid.com/embed/wvy1bcer","https://my.mail.ru/mail/animeizlettr/video/embed/_myvideo/299"]]}],"season_2":[{"episode_1":[["https://video.sibnet.ru/shell.php?videoid=3912096","https://odnoklassniki.ru/videoembed/2660913711699","https://vidmoly.to/embed-nnihlga7lmj3.html","https://sendvid.com/embed/mo1t3qv1","https://my.mail.ru/mail/animeizlettr/video/embed/_myvideo/300"]],"episode_2":[["https://video.sibnet.ru/shell.php?videoid=3912098","https://odnoklassniki.ru/videoembed/2660920461907","https://vidmoly.to/embed-gorzha8193jg.html","https://sendvid.com/embed/oqp0yh9j","https://my.mail.ru/mail/animeizlettr/video/embed/_myvideo/301"]],"episode_3":[["https://video.sibnet.ru/shell.php?videoid=3912101","https://odnoklassniki.ru/videoembed/2660922296915","https://vidmoly.to/embed-tc0zhmtpz3h8.html","https://sendvid.com/embed/rada9l2n","https://my.mail.ru/mail/animeizlettr/video/embed/_myvideo/302"]],"episode_4":[["https://video.sibnet.ru/shell.php?videoid=3912104","https://odnoklassniki.ru/videoembed/2660924656211","https://vidmoly.to/embed-w8t0soa87btl.html","https://sendvid.com/embed/ak8xfp2m","https://my.mail.ru/mail/animeizlettr/video/embed/_myvideo/303"]],"episode_5":[["https://video.sibnet.ru/shell.php?videoid=3912107","https://odnoklassniki.ru/videoembed/2660926884435","https://vidmoly.to/embed-afzfkbbyfleg.html","https://sendvid.com/embed/j2vq87ho","https://my.mail.ru/mail/animeizlettr/video/embed/_myvideo/304"]],"episode_6":[["https://video.sibnet.ru/shell.php?videoid=3912107","https://odnoklassniki.ru/videoembed/2660926884435","https://vidmoly.to/embed-afzfkbbyfleg.html","https://sendvid.com/embed/j2vq87ho","https://my.mail.ru/mail/animeizlettr/video/embed/_myvideo/304"]],"episode_7":[["https://video.sibnet.ru/shell.php?videoid=3912115","https://odnoklassniki.ru/videoembed/2660932651603","https://vidmoly.to/embed-09hlu7k5irw4.html","https://sendvid.com/embed/cpuxanqx","https://my.mail.ru/mail/animeizlettr/video/embed/_myvideo/306"]],"episode_8":[["https://video.sibnet.ru/shell.php?videoid=3912120","https://odnoklassniki.ru/videoembed/2660937304659","https://vidmoly.to/embed-entaurchwzsh.html","https://sendvid.com/embed/bgqlo3s0","https://my.mail.ru/mail/animeizlettr/video/embed/_myvideo/307"]],"episode_9":[["https://video.sibnet.ru/shell.php?videoid=3912125","https://odnoklassniki.ru/videoembed/2660941892179","https://vidmoly.to/embed-zyuvdxk14ps6.html","https://sendvid.com/embed/sxh9h0g4","https://my.mail.ru/mail/animeizlettr/video/embed/_myvideo/308"]],"episode_10":[["https://video.sibnet.ru/shell.php?videoid=3912129","https://odnoklassniki.ru/videoembed/2660946020947","https://vidmoly.to/embed-17sxnj8hl8k6.html","https://sendvid.com/embed/qbow0up6","https://my.mail.ru/mail/animeizlettr/video/embed/_myvideo/309"]]}]}