{"season_1":[{"episode_1":[["https://my.mail.ru/video/embed/7576177045760114843","https://video.sibnet.ru/shell.php?videoid=4002537","https://sendvid.com/embed/1d2cqre6","https://vidsat.net/embed-zrk0qhfgh6rx.html","https://cloudvideo.tv/embed-92e7ilp4ve9u.html","https://drive.google.com/file/d/1VxGteXHiTZZUVC69q-niMpaHQdgFT1Pz/preview","https://odnoklassniki.ru/videoembed/1596497791593"]],"episode_2":[["https://my.mail.ru/video/embed/7576177045760114844","https://video.sibnet.ru/shell.php?videoid=4002543","https://sendvid.com/embed/biqfopjw","https://vidsat.net/embed-1rm29lua1iww.html","https://cloudvideo.tv/embed-lgkotcqu40jf.html","https://drive.google.com/file/d/16_PGOUhIgpJnIecIulXFv3IuFgb2Jgh_/preview","https://odnoklassniki.ru/videoembed/1596499429993"]],"episode_3":[["https://my.mail.ru/video/embed/7576177045760114845","https://video.sibnet.ru/shell.php?videoid=4002547","https://sendvid.com/embed/c08i12yo","https://vidsat.net/embed-m9r5y7gyhybd.html","https://cloudvideo.tv/embed-m3u7tqtx3fwc.html","https://drive.google.com/file/d/1OlcN_rcee4W_DACTCHzh5CCrvbXvfYKX/preview","https://odnoklassniki.ru/videoembed/1596501592681"]],"episode_4":[["https://my.mail.ru/video/embed/7576177045760114846","https://video.sibnet.ru/shell.php?videoid=4002549","https://sendvid.com/embed/44u8w4pg","https://vidsat.net/embed-poreyhzpwcqp.html","https://cloudvideo.tv/embed-jrdrwcokr7ln.html","https://drive.google.com/file/d/1a-mQ4E44Kss8xsCKB6UDw8pYskZ4llEL/preview","https://odnoklassniki.ru/videoembed/1596504279657"]],"episode_5":[["https://my.mail.ru/video/embed/7576177045760114847","https://video.sibnet.ru/shell.php?videoid=4002552","https://sendvid.com/embed/8af0yno5","https://vidsat.net/embed-xycj7dx0m7wr.html","https://cloudvideo.tv/embed-k7c5v4a39vya.html","https://drive.google.com/file/d/1r-iISr2wrYMaNXAQhn4pYG_IzkCiiYen/preview","https://odnoklassniki.ru/videoembed/1596508408425"]],"episode_6":[["https://my.mail.ru/video/embed/7576177045760114848","https://video.sibnet.ru/shell.php?videoid=4002555","https://sendvid.com/embed/hmb2mx71","https://vidsat.net/embed-ve9pwlo87dok.html","https://cloudvideo.tv/embed-0us5c8af39ll.html","https://drive.google.com/file/d/1JX3Y_U3vO6uAl9QFnYBbLtexFa0kBXCw/preview","https://odnoklassniki.ru/videoembed/1596510505577"]],"episode_7":[["https://my.mail.ru/video/embed/7576177045760114849","https://video.sibnet.ru/shell.php?videoid=4002559","https://sendvid.com/embed/llf4gx1k","https://vidsat.net/embed-4voxwu3du087.html","https://cloudvideo.tv/embed-eu0xo22egqp0.html","https://drive.google.com/file/d/1zIbFvbmMCiCNWnAauMfMVpz36I5l_Gbt/preview","https://odnoklassniki.ru/videoembed/1596514896489"]],"episode_8":[["https://my.mail.ru/video/embed/7576177045760114850","https://video.sibnet.ru/shell.php?videoid=4002561","https://sendvid.com/embed/ojlxuz4y","https://vidsat.net/embed-8uq6e957m7ll.html","https://cloudvideo.tv/embed-3pjlx35sf678.html","https://drive.google.com/file/d/1BaDGsP_DIq6ssrVrIMVmOmCCDHKpMFW2/preview","https://odnoklassniki.ru/videoembed/1596516928105"]],"episode_9":[["https://my.mail.ru/video/embed/7576177045760114851","https://video.sibnet.ru/shell.php?videoid=4002564","https://sendvid.com/embed/vz032s32","https://vidsat.net/embed-087jb7ryj8v9.html","https://cloudvideo.tv/embed-1a7jmiyt31ka.html","https://drive.google.com/file/d/1CJMXvST4vcublfau1aaqzNFvmNxJm-xI/preview","https://odnoklassniki.ru/videoembed/1596519090793"]],"episode_10":[["https://my.mail.ru/video/embed/7576177045760114852","https://video.sibnet.ru/shell.php?videoid=4002568","https://sendvid.com/embed/4uejv0ns","https://vidsat.net/embed-nf54eayv0xrn.html","https://cloudvideo.tv/embed-0dgdafiytcs3.html","https://drive.google.com/file/d/1pwmEIs_Q0FOMQUEidQslFP85ul0-USFk/preview","https://odnoklassniki.ru/videoembed/1596522039913"]],"episode_11":[["https://my.mail.ru/video/embed/7576177045760114853","https://video.sibnet.ru/shell.php?videoid=4002573","https://sendvid.com/embed/fiz4qid8","https://vidsat.net/embed-ydchne502qnd.html","https://cloudvideo.tv/embed-jsp90vsf6dpx.html","https://drive.google.com/file/d/1jm5h9WqM3j8viAFniTTXttCh7v7AG_25/preview","https://odnoklassniki.ru/videoembed/1596524071529"]],"episode_12":[["https://my.mail.ru/video/embed/7576177045760114854","https://video.sibnet.ru/shell.php?videoid=4002576","https://sendvid.com/embed/1ogq6cmb","https://vidsat.net/embed-8xegtatxqjwk.html","https://cloudvideo.tv/embed-cyql51dqgb07.html","https://drive.google.com/file/d/16Sd4htTCDVYU1r9XilgAzphqa4_a-Fy-/preview","https://odnoklassniki.ru/videoembed/1596525775465"]]}]}